autonomy-0.1.1.dist-info/licenses/LICENSE
src/__init__.py
src/api/__init__.py
src/api/server.py
src/audit/__init__.py
src/audit/logger.py
src/audit/undo.py
src/cli/__init__.py
src/cli/main.py
src/core/__init__.py
src/core/agents.py
src/core/config.py
src/core/errors.py
src/core/models.py
src/core/platform.py
src/core/secret_vault.py
src/core/workflow.py
src/core/workflow_manager.py
src/github/__init__.py
src/github/board_manager.py
src/github/client.py
src/github/device_flow.py
src/github/issue_manager.py
src/github/pat_scopes.py
src/github/token_storage.py
src/llm/openrouter.py
src/metrics/__init__.py
src/metrics/collector.py
src/metrics/storage.py
src/planning/config.py
src/planning/langgraph_workflow.py
src/planning/workflow.py
src/scaffold/__init__.py
src/slack/__init__.py
src/slack/bot.py
src/slack/commands.py
src/slack/mapping.py
src/slack/notifications.py
src/slack/oauth.py
src/tasks/__init__.py
src/tasks/backlog_doctor.py
src/tasks/hierarchy_manager.py
src/tasks/metrics_service.py
src/tasks/nightly_service.py
src/tasks/pinned_items.py
src/tasks/ranking.py
src/tasks/task_manager.py
src/templates/__init__.py
src/tools/__init__.py
src/tools/github.py
src/tools/memory.py
src/tools/registry.py
src/tools/slack.py
src/utils/distribution.py
autonomy-0.1.1.dist-info/METADATA
autonomy-0.1.1.dist-info/WHEEL
autonomy-0.1.1.dist-info/entry_points.txt
autonomy-0.1.1.dist-info/top_level.txt
autonomy-0.1.1.dist-info/RECORD
