Metadata-Version: 2.4
Name: autonomy
Version: 0.1.1
Summary: Enable human-AI collaboration in software development with the Generate-Verify loop
Author-email: Mehul Bhardwaj <mehul@example.com>
License-Expression: GPL-3.0-or-later
Project-URL: Homepage, https://github.com/mehulbhardwaj/autonomy
Project-URL: Documentation, https://github.com/mehulbhardwaj/autonomy#readme
Project-URL: Repository, https://github.com/mehulbhardwaj/autonomy.git
Project-URL: Issues, https://github.com/mehulbhardwaj/autonomy/issues
Project-URL: Changelog, https://github.com/mehulbhardwaj/autonomy/blob/main/CHANGELOG.md
Keywords: ai,automation,github,workflow,agents,software-development
Classifier: Development Status :: 4 - Beta
Classifier: Intended Audience :: Developers
Classifier: Operating System :: OS Independent
Classifier: Programming Language :: Python :: 3
Classifier: Programming Language :: Python :: 3.8
Classifier: Programming Language :: Python :: 3.9
Classifier: Programming Language :: Python :: 3.10
Classifier: Programming Language :: Python :: 3.11
Classifier: Programming Language :: Python :: 3.12
Classifier: Topic :: Software Development :: Libraries :: Python Modules
Classifier: Topic :: Software Development :: Quality Assurance
Classifier: Topic :: Software Development :: Version Control :: Git
Requires-Python: >=3.8
License-File: LICENSE
Requires-Dist: requests>=2.25.0
Requires-Dist: httpx<0.28,>=0.25.0
Requires-Dist: fastapi>=0.111.0
Requires-Dist: python-multipart>=0.0.5
Requires-Dist: click>=8.0.0
Requires-Dist: pydantic>=2.7.4
Requires-Dist: langgraph>=0.5.4
Requires-Dist: rich>=10.0.0
Requires-Dist: argcomplete>=3.1.1
Requires-Dist: pyyaml>=6.0
Requires-Dist: jinja2>=3.0.0
Requires-Dist: cryptography>=41.0.0
Requires-Dist: langchain-community>=0.0.17
Requires-Dist: mem0ai>=0.1.0
Provides-Extra: dev
Requires-Dist: pytest>=6.0; extra == "dev"
Requires-Dist: pytest-cov>=2.0; extra == "dev"
Requires-Dist: pytest-asyncio>=0.18.0; extra == "dev"
Requires-Dist: black>=21.0; extra == "dev"
Requires-Dist: isort>=5.10; extra == "dev"
Requires-Dist: flake8>=3.8; extra == "dev"
Requires-Dist: mypy>=0.800; extra == "dev"
Requires-Dist: pre-commit>=2.15.0; extra == "dev"
Requires-Dist: keyring>=23.0.0; extra == "dev"
Requires-Dist: argcomplete>=3.1.1; extra == "dev"
Requires-Dist: pyyaml>=6.0; extra == "dev"
Provides-Extra: llm
Requires-Dist: openai>=1.0.0; extra == "llm"
Requires-Dist: anthropic>=0.3.0; extra == "llm"
Dynamic: license-file
